eascheduler/__init__.py
eascheduler/__version__.py
eascheduler/const.py
eascheduler/default.py
eascheduler/py.typed
eascheduler/builder/__init__.py
eascheduler/builder/filters.py
eascheduler/builder/helper.py
eascheduler/builder/jobs.py
eascheduler/builder/triggers.py
eascheduler/builder/utils.py
eascheduler/errors/__init__.py
eascheduler/errors/errors.py
eascheduler/errors/handler.py
eascheduler/executor/__init__.py
eascheduler/executor/base.py
eascheduler/helpers/__init__.py
eascheduler/helpers/dst_param.py
eascheduler/helpers/helpers.py
eascheduler/helpers/time_replace.py
eascheduler/job_control/__init__.py
eascheduler/job_control/base.py
eascheduler/job_control/job_countdown.py
eascheduler/job_control/job_datetime.py
eascheduler/job_control/job_onetime.py
eascheduler/job_stores/__init__.py
eascheduler/job_stores/base.py
eascheduler/job_stores/memory.py
eascheduler/jobs/__init__.py
eascheduler/jobs/base.py
eascheduler/jobs/event_handler.py
eascheduler/jobs/job_countdown.py
eascheduler/jobs/job_datetime.py
eascheduler/jobs/job_onetime.py
eascheduler/producers/__init__.py
eascheduler/producers/base.py
eascheduler/producers/prod_filter.py
eascheduler/producers/prod_filter_holiday.py
eascheduler/producers/prod_group.py
eascheduler/producers/prod_interval.py
eascheduler/producers/prod_operation.py
eascheduler/producers/prod_sun.py
eascheduler/producers/prod_time.py
eascheduler/schedulers/__init__.py
eascheduler/schedulers/async_scheduler.py
eascheduler/schedulers/base.py
eascheduler/task_managers/__init__.py
eascheduler/task_managers/base.py
eascheduler/task_managers/parallel.py
eascheduler/task_managers/sequential.py
eascheduler-0.2.7.dist-info/licenses/LICENSE
eascheduler-0.2.7.dist-info/METADATA
eascheduler-0.2.7.dist-info/WHEEL
eascheduler-0.2.7.dist-info/top_level.txt
eascheduler-0.2.7.dist-info/RECORD
