Metadata-Version: 2.4
Name: EAScheduler
Version: 0.2.7
Summary: Easy async scheduling with a nice interface
Home-page: https://github.com/spacemanspiff2007/eascheduler
Author: spaceman_spiff
Project-URL: Documentation, https://eascheduler.readthedocs.io/
Project-URL: GitHub, https://github.com/spacemanspiff2007/eascheduler
Keywords: scheduler,asyncio
Classifier: Development Status :: 4 - Beta
Classifier: Framework :: AsyncIO
Classifier: License :: OSI Approved :: Apache Software License
Classifier: Operating System :: OS Independent
Classifier: Programming Language :: Python :: 3.10
Classifier: Programming Language :: Python :: 3.11
Classifier: Programming Language :: Python :: 3.12
Classifier: Programming Language :: Python :: 3.13
Classifier: Programming Language :: Python :: 3 :: Only
Requires-Python: >=3.10
License-File: LICENSE
Requires-Dist: whenever==0.8.8
Requires-Dist: astral==3.2
Requires-Dist: holidays==0.79
Requires-Dist: typing_extensions
Dynamic: author
Dynamic: classifier
Dynamic: description
Dynamic: description-content-type
Dynamic: home-page
Dynamic: keywords
Dynamic: license-file
Dynamic: project-url
Dynamic: requires-dist
Dynamic: requires-python
Dynamic: summary
